reverse_engineered_apis/__init__.py
reverse_engineered_apis/flatastic/__init__.py
reverse_engineered_apis/flatastic/api_client.py
reverse_engineered_apis/flatastic/api_response.py
reverse_engineered_apis/flatastic/configuration.py
reverse_engineered_apis/flatastic/exceptions.py
reverse_engineered_apis/flatastic/py.typed
reverse_engineered_apis/flatastic/rest.py
reverse_engineered_apis/flatastic/api/__init__.py
reverse_engineered_apis/flatastic/api/auth_api.py
reverse_engineered_apis/flatastic/api/cashflow_api.py
reverse_engineered_apis/flatastic/api/chores_api.py
reverse_engineered_apis/flatastic/api/shoppinglist_api.py
reverse_engineered_apis/flatastic/api/shouts_api.py
reverse_engineered_apis/flatastic/api/subscriptions_api.py
reverse_engineered_apis/flatastic/api/user_api.py
reverse_engineered_apis/flatastic/api/wg_api.py
reverse_engineered_apis/flatastic/models/__init__.py
reverse_engineered_apis/flatastic/models/get_cashflow200_response_inner.py
reverse_engineered_apis/flatastic/models/get_cashflow200_response_inner_items_inner.py
reverse_engineered_apis/flatastic/models/get_cashflow200_response_inner_items_inner_cost_allocation_inner.py
reverse_engineered_apis/flatastic/models/get_cashflow_statistics200_response_inner.py
reverse_engineered_apis/flatastic/models/get_chores200_response_inner.py
reverse_engineered_apis/flatastic/models/get_chores_statistics200_response.py
reverse_engineered_apis/flatastic/models/get_logout200_response.py
reverse_engineered_apis/flatastic/models/get_my_expenses200_response_inner.py
reverse_engineered_apis/flatastic/models/get_shoppinglist200_response_inner.py
reverse_engineered_apis/flatastic/models/get_shouts200_response_inner.py
reverse_engineered_apis/flatastic/models/get_wg200_response.py
reverse_engineered_apis/flatastic/models/get_wg200_response_flatmates_inner.py
reverse_engineered_apis/flatastic/models/post_change_pw_request.py
reverse_engineered_apis/flatastic/models/post_chores200_response.py
reverse_engineered_apis.flatastic-24.4.14rc184927.dist-info/LICENSE
reverse_engineered_apis.flatastic-24.4.14rc184927.dist-info/METADATA
reverse_engineered_apis.flatastic-24.4.14rc184927.dist-info/WHEEL
reverse_engineered_apis.flatastic-24.4.14rc184927.dist-info/top_level.txt
reverse_engineered_apis.flatastic-24.4.14rc184927.dist-info/RECORD
