Metadata-Version: 2.1
Name: reverse-engineered-apis.flatastic
Version: 24.4.14rc184927
Summary: flatastic API Schema
Home-page: 
Author: Reverse Engineered APIs
Author-email: tim+reverse-engineered-apis@vahlbrock.de
Keywords: OpenAPI,OpenAPI-Generator,Flatastic API Schema
License-File: LICENSE
Requires-Dist: urllib3 <2.1.0,>=1.25.3
Requires-Dist: python-dateutil
Requires-Dist: pydantic >=2
Requires-Dist: typing-extensions >=4.7.1
